pyheatintegration/__init__.py
pyheatintegration/base_range.py
pyheatintegration/enums.py
pyheatintegration/errors.py
pyheatintegration/grand_composite_curve.py
pyheatintegration/heat_exchanger.py
pyheatintegration/heat_range.py
pyheatintegration/line.py
pyheatintegration/pinch_analyzer.py
pyheatintegration/plot_segment.py
pyheatintegration/segment.py
pyheatintegration/temperature_range.py
pyheatintegration/tq_diagram.py
pyheatintegration/streams/__init__.py
pyheatintegration/streams/streams.py
pyheatintegration/streams/utilities.py
pyheatintegration-0.6.1.dist-info/LICENSE
pyheatintegration-0.6.1.dist-info/METADATA
pyheatintegration-0.6.1.dist-info/WHEEL
pyheatintegration-0.6.1.dist-info/top_level.txt
pyheatintegration-0.6.1.dist-info/RECORD
